{
  "doi": "10.3390/ijerph17155605",
  "slug": "10.3390-ijerph17155605",
  "title": "Schoolteachers’ Knowledge of Attention-Deficit/ Hyperactivity Disorder—Current Status and Effectiveness of Knowledge Improvement Program: A Randomized Controlled Trial",
  "abstract": "<strong>Background:</strong> Adequately knowledgeable schoolteachers can play an essential role in early detection and proper treatment of children with attention-deficit/hyperactivity disorder (ADHD) at school.",
  "categories": [
    "Uncategorized"
  ],
  "authors": [
    {
      "given": "Abdullah M.",
      "family": "Alshehri",
      "sequence": 1
    },
    {
      "given": "Shehata F.",
      "family": "Shehata",
      "sequence": 2
    },
    {
      "given": "Khalid M.",
      "family": "Almosa",
      "sequence": 3
    },
    {
      "given": "Nabil J.",
      "family": "Awadalla",
      "orcid": "https://orcid.org/0000-0002-5687-6621",
      "sequence": 4
    }
  ],
  "access": {
    "status": "open",
    "sourceUrl": "https://www.mdpi.com/1660-4601/17/15/5605/pdf?version=1596515020",
    "license": "cc-by"
  },
  "visibility": {
    "hidden": false
  },
  "id": "doi-10.3390-ijerph17155605",
  "publication": {
    "year": 2020
  },
  "journal": {
    "name": "International Journal of Environmental Research and Public Health",
    "issn": "1660-4601",
    "volume": "17",
    "issue": "15",
    "pages": {
      "start": "5605",
      "end": null
    }
  },
  "identifiers": {
    "doi": "10.3390/ijerph17155605"
  },
  "language": "English"
}
